{
    "platformName": "Android",
    "platformVersion": "5.1.1",
    "deviceName": "ASUS_X013D",
    "automationName": "UiAutomator2",
    "newCommandTimeout": 60,
    "udid": "",
    "orientation": "LANDSCAPE",
    "browserName": "Chrome",
    "printPageSourceOnFindFailure": true,
    "app": "C:\\appium\\automation_mobile\\appium_automation\\cucumber\\app",
	"appPackage": "br.net.nimbi.outsystems01.NimbiDrive",
	"appActivity": ".MainActivity",
    "appWaitDuration": 3000,
    "adbPort": 5037,
    "isHeadless": false,
    "systemPort": 8200
}